pyxwb2/__init__.py
pyxwb2/pyxwb2.py
pyxwb2/utils.py
pyxwb2/data/dial-maneuvers-conversion.json
pyxwb2/data/ffg-xws.json
pyxwb2/data/manifest.json
pyxwb2/data/translation.json
pyxwb2/data/xws_schema.json
pyxwb2/data/actions/actions.json
pyxwb2/data/conditions/conditions.json
pyxwb2/data/damage-decks/core.json
pyxwb2/data/data/ffg-xws.json
pyxwb2/data/data/manifest.json
pyxwb2/data/data/translation.json
pyxwb2/data/data/actions/actions.json
pyxwb2/data/data/conditions/conditions.json
pyxwb2/data/data/damage-decks/core.json
pyxwb2/data/data/factions/factions.json
pyxwb2/data/data/pilots/first-order/tie-ba-interceptor.json
pyxwb2/data/data/pilots/first-order/tie-fo-fighter.json
pyxwb2/data/data/pilots/first-order/tie-sf-fighter.json
pyxwb2/data/data/pilots/first-order/tie-vn-silencer.json
pyxwb2/data/data/pilots/first-order/upsilon-class-command-shuttle.json
pyxwb2/data/data/pilots/first-order/xi-class-light-shuttle.json
pyxwb2/data/data/pilots/galactic-empire/alpha-class-star-wing.json
pyxwb2/data/data/pilots/galactic-empire/lambda-class-t-4a-shuttle.json
pyxwb2/data/data/pilots/galactic-empire/tie-advanced-v1.json
pyxwb2/data/data/pilots/galactic-empire/tie-advanced-x1.json
pyxwb2/data/data/pilots/galactic-empire/tie-ag-aggressor.json
pyxwb2/data/data/pilots/galactic-empire/tie-ca-punisher.json
pyxwb2/data/data/pilots/galactic-empire/tie-d-defender.json
pyxwb2/data/data/pilots/galactic-empire/tie-in-interceptor.json
pyxwb2/data/data/pilots/galactic-empire/tie-ln-fighter.json
pyxwb2/data/data/pilots/galactic-empire/tie-ph-phantom.json
pyxwb2/data/data/pilots/galactic-empire/tie-rb-heavy.json
pyxwb2/data/data/pilots/galactic-empire/tie-reaper.json
pyxwb2/data/data/pilots/galactic-empire/tie-sa-bomber.json
pyxwb2/data/data/pilots/galactic-empire/tie-sk-striker.json
pyxwb2/data/data/pilots/galactic-empire/vt-49-decimator.json
pyxwb2/data/data/pilots/galactic-republic/arc-170-starfighter.json
pyxwb2/data/data/pilots/galactic-republic/btl-b-y-wing.json
pyxwb2-0.2.1b0.dist-info/METADATA
pyxwb2-0.2.1b0.dist-info/WHEEL
pyxwb2-0.2.1b0.dist-info/top_level.txt
pyxwb2-0.2.1b0.dist-info/RECORD
